archerdfu/bmp/__init__.py
archerdfu/bmp/__main__.py
archerdfu/bmp/caliber_icons.py
archerdfu/bmp/framebuf.py
archerdfu/bmp/gui_fonts.py
archerdfu/bmp/processing.py
archerdfu/bmp/__pyinstaller/__init__.py
archerdfu/bmp/__pyinstaller/hook-archerdfu.py
archerdfu/bmp/fonts/default.flf
archerdfu/bmp/fonts/pixel.flf
archerdfu/bmp/reticle/__init__.py
archerdfu/bmp/reticle/elements.py
archerdfu/bmp/reticle/reticle.py
archerdfu.bmp-1.0.4.dist-info/LICENSE
archerdfu.bmp-1.0.4.dist-info/METADATA
archerdfu.bmp-1.0.4.dist-info/WHEEL
archerdfu.bmp-1.0.4.dist-info/entry_points.txt
archerdfu.bmp-1.0.4.dist-info/top_level.txt
archerdfu.bmp-1.0.4.dist-info/RECORD
